scratchrelaxtv/__init__.py
scratchrelaxtv/cli.py
scratchrelaxtv/logging.conf
scratchrelaxtv-0.6.17.dist-info/LICENSE
scratchrelaxtv-0.6.17.dist-info/METADATA
scratchrelaxtv-0.6.17.dist-info/WHEEL
scratchrelaxtv-0.6.17.dist-info/entry_points.txt
scratchrelaxtv-0.6.17.dist-info/top_level.txt
scratchrelaxtv-0.6.17.dist-info/RECORD
